azureml/__init__.py
azureml/contrib/__init__.py
azureml/contrib/automl/__init__.py
azureml/contrib/automl/dnn/__init__.py
azureml/contrib/automl/dnn/vision/__init__.py
azureml/contrib/automl/dnn/vision/classification/__init__.py
azureml/contrib/automl/dnn/vision/classification/runner.py
azureml/contrib/automl/dnn/vision/classification/common/__init__.py
azureml/contrib/automl/dnn/vision/classification/common/classification_utils.py
azureml/contrib/automl/dnn/vision/classification/common/constants.py
azureml/contrib/automl/dnn/vision/classification/common/transforms.py
azureml/contrib/automl/dnn/vision/classification/inference/__init__.py
azureml/contrib/automl/dnn/vision/classification/inference/score.py
azureml/contrib/automl/dnn/vision/classification/io/__init__.py
azureml/contrib/automl/dnn/vision/classification/io/read/__init__.py
azureml/contrib/automl/dnn/vision/classification/io/read/dataloader.py
azureml/contrib/automl/dnn/vision/classification/io/read/dataset_wrappers.py
azureml/contrib/automl/dnn/vision/classification/io/read/utils.py
azureml/contrib/automl/dnn/vision/classification/io/write/__init__.py
azureml/contrib/automl/dnn/vision/classification/io/write/featurize_script.py
azureml/contrib/automl/dnn/vision/classification/io/write/score_script.py
azureml/contrib/automl/dnn/vision/classification/io/write/score_script_utils.py
azureml/contrib/automl/dnn/vision/classification/models/__init__.py
azureml/contrib/automl/dnn/vision/classification/models/base_model_wrapper.py
azureml/contrib/automl/dnn/vision/classification/models/classification_model_wrappers.py
azureml/contrib/automl/dnn/vision/classification/trainer/__init__.py
azureml/contrib/automl/dnn/vision/classification/trainer/criterion.py
azureml/contrib/automl/dnn/vision/classification/trainer/train.py
azureml/contrib/automl/dnn/vision/common/NOTICE
azureml/contrib/automl/dnn/vision/common/__init__.py
azureml_contrib_automl_dnn_vision-1.32.0.dist-info/DESCRIPTION.rst
azureml_contrib_automl_dnn_vision-1.32.0.dist-info/LICENSE.txt
azureml_contrib_automl_dnn_vision-1.32.0.dist-info/METADATA
azureml_contrib_automl_dnn_vision-1.32.0.dist-info/RECORD
azureml_contrib_automl_dnn_vision-1.32.0.dist-info/WHEEL
azureml_contrib_automl_dnn_vision-1.32.0.dist-info/metadata.json
azureml_contrib_automl_dnn_vision-1.32.0.dist-info/namespace_packages.txt
azureml_contrib_automl_dnn_vision-1.32.0.dist-info/top_level.txt
